{
  "lightStyle": "minimal-light",
  "darkStyle": "minimal-dark",
  "lightScheme": "minimal-default-light",
  "darkScheme": "minimal-default-dark",
  "editorFont": "",
  "lineHeight": 1.5,
  "lineWidth": 60,
  "lineWidthWide": 70,
  "maxWidth": 95,
  "textNormal": 20,
  "textSmall": 16,
  "imgGrid": true,
  "imgWidth": "img-wide",
  "tableWidth": "table-100",
  "iframeWidth": "iframe-100",
  "mapWidth": "map-100",
  "chartWidth": "chart-100",
  "colorfulHeadings": true,
  "colorfulFrame": true,
  "colorfulActiveStates": true,
  "trimNames": true,
  "labeledNav": true,
  "fullWidthMedia": true,
  "bordersToggle": true,
  "minimalStatus": true,
  "focusMode": true,
  "underlineInternal": true,
  "underlineExternal": true,
  "folding": true,
  "lineNumbers": false,
  "readableLineLength": true,
  "devBlockWidth": false
}